<svg 
 xmlns="http://www.w3.org/2000/svg"
 xmlns:xlink="http://www.w3.org/1999/xlink"
 width="1441px" height="1016px">
<defs>
<linearGradient id="PSgrad_0" x1="0%" x2="0%" y1="100%" y2="0%">
  <stop offset="0%" stop-color="rgb(255,255,255)" stop-opacity="0" />
  <stop offset="100%" stop-color="rgb(255,255,255)" stop-opacity="1" />
</linearGradient>

</defs>
<path fill-rule="evenodd"  opacity="0.302" fill="rgb(205, 249, 255)"
 d="M1441.000,982.999 C1441.000,982.999 1253.482,1015.998 1002.696,1015.998 C819.427,1015.998 578.591,969.998 411.285,969.998 C151.692,969.998 0.000,997.998 0.000,997.998 L0.000,-0.003 L1441.000,-0.003 L1441.000,982.999 Z"/>
<path fill="url(#PSgrad_0)"
 d="M1441.000,982.999 C1441.000,982.999 1253.482,1015.998 1002.696,1015.998 C819.427,1015.998 578.591,969.998 411.285,969.998 C151.692,969.998 0.000,997.998 0.000,997.998 L0.000,-0.003 L1441.000,-0.003 L1441.000,982.999 Z"/>
</svg>